ccowsay.py
ccowsay-1.2.3.dist-info/LICENSE
ccowsay-1.2.3.dist-info/METADATA
ccowsay-1.2.3.dist-info/WHEEL
ccowsay-1.2.3.dist-info/entry_points.txt
ccowsay-1.2.3.dist-info/RECORD
