Metadata-Version: 2.3
Name: ccowsay
Version: 1.2.3
Summary: A tool for generating customizable ASCII art messages with speech bubbles and cow-style templates, supporting styled text using AnsiMarkup.
Author: Ashkan Feyzollahi
Author-email: ashkanfeyzollahi@gmail.com
Requires-Python: >=3.11,<4.0
Classifier: Programming Language :: Python :: 3
Classifier: Programming Language :: Python :: 3.11
Classifier: Programming Language :: Python :: 3.12
Classifier: Programming Language :: Python :: 3.13
Requires-Dist: ansimarkup (>=2.1.0,<3.0.0)
Requires-Dist: appdirs (>=1.4.4,<2.0.0)
Requires-Dist: cli-box (>=0.2.0,<0.3.0)
Requires-Dist: click (>=8.3.0,<9.0.0)
Requires-Dist: requests (>=2.32.5,<3.0.0)
